[{"awards_year":2024,"collectionId":"pbc_1952181814","collectionName":"view_list_year_details","created":"2025-01-08 09:08:40.898Z","id":"n1rcjb97tup8v6b","list_id":"805i80439wq5971","list_name":"Booker Prize","list_slug":"booker-prize","list_year":2024,"list_year_buid":"7qnrrn","list_year_extended_display_name":"","list_year_name":"2024 Booker Prize","list_year_slug":"","list_year_source":"","short_description":""},{"awards_year":2023,"collectionId":"pbc_1952181814","collectionName":"view_list_year_details","created":"2025-01-08 11:03:39.677Z","id":"m97f1p3opx85p7s","list_id":"805i80439wq5971","list_name":"Booker Prize","list_slug":"booker-prize","list_year":2023,"list_year_buid":"kdmfhr","list_year_extended_display_name":"","list_year_name":"2023 Booker Prize","list_year_slug":"","list_year_source":"https://thebookerprizes.com/the-booker-library/prize-years/2023","short_description":""},{"awards_year":2022,"collectionId":"pbc_1952181814","collectionName":"view_list_year_details","created":"2025-01-08 11:18:14.993Z","id":"whs20kpw8061d9y","list_id":"805i80439wq5971","list_name":"Booker Prize","list_slug":"booker-prize","list_year":2022,"list_year_buid":"rwzk7m","list_year_extended_display_name":"","list_year_name":"2022 Booker Prize","list_year_slug":"","list_year_source":"https://thebookerprizes.com/the-booker-library/prize-years/2022","short_description":""},{"awards_year":2021,"collectionId":"pbc_1952181814","collectionName":"view_list_year_details","created":"2025-01-08 11:23:09.830Z","id":"9623cbag4rar481","list_id":"805i80439wq5971","list_name":"Booker Prize","list_slug":"booker-prize","list_year":2021,"list_year_buid":"6gctpp","list_year_extended_display_name":"","list_year_name":"2021 Booker Prize","list_year_slug":"","list_year_source":"https://thebookerprizes.com/the-booker-library/prize-years/2021","short_description":""},{"awards_year":2020,"collectionId":"pbc_1952181814","collectionName":"view_list_year_details","created":"2025-01-09 00:29:17.318Z","id":"y9ux041qk8ryaef","list_id":"805i80439wq5971","list_name":"Booker Prize","list_slug":"booker-prize","list_year":2020,"list_year_buid":"j8qwr7","list_year_extended_display_name":"","list_year_name":"2020 Booker Prize","list_year_slug":"","list_year_source":"https://thebookerprizes.com/the-booker-library/prize-years/2020","short_description":""},{"awards_year":2019,"collectionId":"pbc_1952181814","collectionName":"view_list_year_details","created":"2025-01-09 00:32:36.992Z","id":"urd9ud75461565w","list_id":"805i80439wq5971","list_name":"Booker Prize","list_slug":"booker-prize","list_year":2019,"list_year_buid":"wf7z7k","list_year_extended_display_name":"","list_year_name":"2019 Booker Prize","list_year_slug":"","list_year_source":"https://thebookerprizes.com/the-booker-library/prize-years/2019","short_description":""},{"awards_year":2018,"collectionId":"pbc_1952181814","collectionName":"view_list_year_details","created":"2025-01-11 09:11:16.643Z","id":"67kk3zp294f1qxu","list_id":"805i80439wq5971","list_name":"Booker Prize","list_slug":"booker-prize","list_year":2018,"list_year_buid":"7fcrjg","list_year_extended_display_name":"The Man Booker Prize","list_year_name":"2018 Booker Prize","list_year_slug":"","list_year_source":"https://thebookerprizes.com/the-booker-library/prize-years/2018","short_description":""},{"awards_year":2017,"collectionId":"pbc_1952181814","collectionName":"view_list_year_details","created":"2025-01-11 09:23:01.821Z","id":"5qy35535467c3t4","list_id":"805i80439wq5971","list_name":"Booker Prize","list_slug":"booker-prize","list_year":2017,"list_year_buid":"t6gjjz","list_year_extended_display_name":"The Man Booker Prize","list_year_name":"2017 Booker Prize","list_year_slug":"","list_year_source":"","short_description":""},{"awards_year":2016,"collectionId":"pbc_1952181814","collectionName":"view_list_year_details","created":"2025-01-11 09:29:26.863Z","id":"3v86w6566cbljc2","list_id":"805i80439wq5971","list_name":"Booker Prize","list_slug":"booker-prize","list_year":2016,"list_year_buid":"mn87gg","list_year_extended_display_name":"The Man Booker Prize","list_year_name":"2016 Booker Prize","list_year_slug":"","list_year_source":"","short_description":""},{"awards_year":2015,"collectionId":"pbc_1952181814","collectionName":"view_list_year_details","created":"2025-01-11 09:32:06.796Z","id":"9qt439gffom3r52","list_id":"805i80439wq5971","list_name":"Booker Prize","list_slug":"booker-prize","list_year":2015,"list_year_buid":"pwp9cr","list_year_extended_display_name":"","list_year_name":"2015 Booker Prize","list_year_slug":"","list_year_source":"","short_description":""},{"awards_year":2014,"collectionId":"pbc_1952181814","collectionName":"view_list_year_details","created":"2025-01-11 21:14:55.084Z","id":"s7va8p523a1243o","list_id":"805i80439wq5971","list_name":"Booker Prize","list_slug":"booker-prize","list_year":2014,"list_year_buid":"tn9krk","list_year_extended_display_name":"","list_year_name":"2014 Booker Prize","list_year_slug":"","list_year_source":"","short_description":""},{"awards_year":2024,"collectionId":"pbc_1952181814","collectionName":"view_list_year_details","created":"2025-01-21 08:53:44.853Z","id":"savzu3t6tk7hy9f","list_id":"7cd04i0mg4jt4pn","list_name":"International Booker Prize","list_slug":"international-booker-prize","list_year":2024,"list_year_buid":"zp9kg8","list_year_extended_display_name":"","list_year_name":"2024 International Booker Prize","list_year_slug":"","list_year_source":"https://thebookerprizes.com/the-booker-library/prize-years/international/2024","short_description":""},{"awards_year":2023,"collectionId":"pbc_1952181814","collectionName":"view_list_year_details","created":"2025-01-24 07:56:28.751Z","id":"55180xz54y5723s","list_id":"7cd04i0mg4jt4pn","list_name":"International Booker Prize","list_slug":"international-booker-prize","list_year":2023,"list_year_buid":"qkrmqc","list_year_extended_display_name":"","list_year_name":"2023 International Booker Prize","list_year_slug":"","list_year_source":"https://thebookerprizes.com/the-booker-library/prize-years/international/2023","short_description":""},{"awards_year":2023,"collectionId":"pbc_1952181814","collectionName":"view_list_year_details","created":"2025-01-26 07:25:37.641Z","id":"e25yr0pd5kg9r0g","list_id":"9n9z6173a9ge398","list_name":"Nebula Award for Best Novel","list_slug":"nebula-award-best-novel","list_year":2023,"list_year_buid":"n6bz77","list_year_extended_display_name":"","list_year_name":"2023 Nebula Award for Best Novel","list_year_slug":"","list_year_source":"https://nebulas.sfwa.org/award-year/2023/","short_description":""},{"awards_year":2022,"collectionId":"pbc_1952181814","collectionName":"view_list_year_details","created":"2025-01-26 07:41:50.257Z","id":"6r4wz27nuho8523","list_id":"9n9z6173a9ge398","list_name":"Nebula Award for Best Novel","list_slug":"nebula-award-best-novel","list_year":2022,"list_year_buid":"zfk9bp","list_year_extended_display_name":"","list_year_name":"2022 Nebula Award for Best Novel","list_year_slug":"","list_year_source":"https://nebulas.sfwa.org/award-year/2022/","short_description":""},{"awards_year":2021,"collectionId":"pbc_1952181814","collectionName":"view_list_year_details","created":"2025-01-26 07:41:58.041Z","id":"b0e83n948q4w74p","list_id":"9n9z6173a9ge398","list_name":"Nebula Award for Best Novel","list_slug":"nebula-award-best-novel","list_year":2021,"list_year_buid":"gmcd7n","list_year_extended_display_name":"","list_year_name":"2021 Nebula Award for Best Novel","list_year_slug":"","list_year_source":"https://nebulas.sfwa.org/award-year/2021/","short_description":""},{"awards_year":2020,"collectionId":"pbc_1952181814","collectionName":"view_list_year_details","created":"2025-01-26 07:47:02.032Z","id":"76jk3e06hlu0390","list_id":"9n9z6173a9ge398","list_name":"Nebula Award for Best Novel","list_slug":"nebula-award-best-novel","list_year":2020,"list_year_buid":"9grjtz","list_year_extended_display_name":"","list_year_name":"2020 Nebula Award for Best Novel","list_year_slug":"","list_year_source":"https://nebulas.sfwa.org/award-year/2020/","short_description":""},{"awards_year":2019,"collectionId":"pbc_1952181814","collectionName":"view_list_year_details","created":"2025-01-26 08:06:23.731Z","id":"3g9d77cutex8h80","list_id":"9n9z6173a9ge398","list_name":"Nebula Award for Best Novel","list_slug":"nebula-award-best-novel","list_year":2019,"list_year_buid":"mkdfmm","list_year_extended_display_name":"","list_year_name":"2019 Nebula Award for Best Novel","list_year_slug":"","list_year_source":"https://nebulas.sfwa.org/award-year/2019","short_description":""},{"awards_year":2022,"collectionId":"pbc_1952181814","collectionName":"view_list_year_details","created":"2025-01-26 08:16:13.678Z","id":"0i18l64kek61f2w","list_id":"7cd04i0mg4jt4pn","list_name":"International Booker Prize","list_slug":"international-booker-prize","list_year":2022,"list_year_buid":"7q86wk","list_year_extended_display_name":"","list_year_name":"2022 International Booker Prize","list_year_slug":"","list_year_source":"https://thebookerprizes.com/the-booker-library/prize-years/international/2022","short_description":""},{"awards_year":2023,"collectionId":"pbc_1952181814","collectionName":"view_list_year_details","created":"2025-01-29 10:03:26.091Z","id":"2591rb5l7rak9vs","list_id":"48k2liyb6531cf9","list_name":"Hugo Award for Best Novel","list_slug":"hugo-award-best-novel","list_year":2024,"list_year_buid":"8dd8br","list_year_extended_display_name":"","list_year_name":"2024 Hugo Award for Best Novel","list_year_slug":"","list_year_source":"https://www.thehugoawards.org/hugo-history/2024-hugo-awards/","short_description":""},{"awards_year":2022,"collectionId":"pbc_1952181814","collectionName":"view_list_year_details","created":"2025-01-29 10:03:32.302Z","id":"a6b50almgu5w190","list_id":"48k2liyb6531cf9","list_name":"Hugo Award for Best Novel","list_slug":"hugo-award-best-novel","list_year":2023,"list_year_buid":"ndbrkm","list_year_extended_display_name":"","list_year_name":"2023 Hugo Award for Best Novel","list_year_slug":"","list_year_source":"https://www.thehugoawards.org/hugo-history/2023-hugo-awards/","short_description":""},{"awards_year":2024,"collectionId":"pbc_1952181814","collectionName":"view_list_year_details","created":"2025-01-29 22:02:27.471Z","id":"6s4hn7t0the8461","list_id":"8q7w4r04n5rbm69","list_name":"New Zealand Book Award for Fiction","list_slug":"new-zealand-book-award-fiction","list_year":2024,"list_year_buid":"69878z","list_year_extended_display_name":"Jann Medlicott Acorn Prize For Fiction","list_year_name":"2024 New Zealand Book Award for Fiction","list_year_slug":"","list_year_source":"https://www.nzbookawards.nz/new-zealand-book-awards/2024-awards/longlist/","short_description":""},{"awards_year":2023,"collectionId":"pbc_1952181814","collectionName":"view_list_year_details","created":"2025-01-29 22:12:45.156Z","id":"tsgn56xp26q282q","list_id":"8q7w4r04n5rbm69","list_name":"New Zealand Book Award for Fiction","list_slug":"new-zealand-book-award-fiction","list_year":2023,"list_year_buid":"hrcnc6","list_year_extended_display_name":"Jann Medlicott Acorn Prize For Fiction","list_year_name":"2023 New Zealand Book Award for Fiction","list_year_slug":"","list_year_source":"https://www.nzbookawards.nz/new-zealand-book-awards/2023-awards/longlist/","short_description":""},{"awards_year":2022,"collectionId":"pbc_1952181814","collectionName":"view_list_year_details","created":"2025-01-29 22:36:09.217Z","id":"8f639p74892o2gd","list_id":"8q7w4r04n5rbm69","list_name":"New Zealand Book Award for Fiction","list_slug":"new-zealand-book-award-fiction","list_year":2022,"list_year_buid":"b97mqd","list_year_extended_display_name":"Jann Medlicott Acorn Prize For Fiction","list_year_name":"2022 New Zealand Book Award for Fiction","list_year_slug":"","list_year_source":"https://www.nzbookawards.nz/new-zealand-book-awards/2022-awards/longlist/","short_description":""},{"awards_year":2025,"collectionId":"pbc_1952181814","collectionName":"view_list_year_details","created":"2025-02-03 22:47:12.046Z","id":"fz67443t8636l82","list_id":"8q7w4r04n5rbm69","list_name":"New Zealand Book Award for Fiction","list_slug":"new-zealand-book-award-fiction","list_year":2025,"list_year_buid":"z7jkdh","list_year_extended_display_name":"","list_year_name":"2025 New Zealand Book Award for Fiction","list_year_slug":"","list_year_source":"https://www.nzbookawards.nz/new-zealand-book-awards/2025-awards/longlist/","short_description":""},{"awards_year":1968,"collectionId":"pbc_1952181814","collectionName":"view_list_year_details","created":"2025-02-09 08:17:28.554Z","id":"pn3c4l76di356mb","list_id":"805i80439wq5971","list_name":"Booker Prize","list_slug":"booker-prize","list_year":1969,"list_year_buid":"cmgkb6","list_year_extended_display_name":"","list_year_name":"1969 Booker Prize","list_year_slug":"","list_year_source":"https://thebookerprizes.com/the-booker-library/prize-years/1969","short_description":""},{"awards_year":1969,"collectionId":"pbc_1952181814","collectionName":"view_list_year_details","created":"2025-02-09 08:19:26.760Z","id":"7kj7d9g3x9gpd5u","list_id":"805i80439wq5971","list_name":"Booker Prize","list_slug":"booker-prize","list_year":1970,"list_year_buid":"nmz76z","list_year_extended_display_name":"","list_year_name":"1970 Booker Prize","list_year_slug":"","list_year_source":"https://thebookerprizes.com/the-booker-library/prize-years/1970","short_description":""},{"awards_year":1971,"collectionId":"pbc_1952181814","collectionName":"view_list_year_details","created":"2025-02-09 08:19:43.406Z","id":"c8g637d3ks88me1","list_id":"805i80439wq5971","list_name":"Booker Prize","list_slug":"booker-prize","list_year":1971,"list_year_buid":"9ctdkq","list_year_extended_display_name":"","list_year_name":"1971 Booker Prize","list_year_slug":"","list_year_source":"https://thebookerprizes.com/the-booker-library/prize-years/1971","short_description":""},{"awards_year":1970,"collectionId":"pbc_1952181814","collectionName":"view_list_year_details","created":"2025-02-09 08:41:48.156Z","id":"9d690e1de0z2s6j","list_id":"805i80439wq5971","list_name":"Booker Prize","list_slug":"booker-prize","list_year":1970,"list_year_buid":"bqprfp","list_year_extended_display_name":"The Lost Man Booker","list_year_name":"1970 Lost Booker Prize","list_year_slug":"1970-lost","list_year_source":"https://thebookerprizes.com/the-lost-man-booker","short_description":"In 1970, the Booker Prize changed its award schedule, resulting a one-time group of books which were ineligible for the award. Years later, they awarded this Lost Booker Prize to recognize those books."},{"awards_year":2024,"collectionId":"pbc_1952181814","collectionName":"view_list_year_details","created":"2025-02-16 08:27:25.274Z","id":"z7uh7dw9f7pf7bt","list_id":"r204xjwf2flc2k3","list_name":"National Book Award","list_slug":"national-book-award","list_year":2024,"list_year_buid":"mk66mp","list_year_extended_display_name":"","list_year_name":"2024 National Book Award","list_year_slug":"","list_year_source":"https://www.nationalbook.org/awards-prizes/national-book-awards-2024/","short_description":""},{"awards_year":2024,"collectionId":"pbc_1952181814","collectionName":"view_list_year_details","created":"2025-02-16 08:38:56.407Z","id":"dijuu9l0mblit1l","list_id":"74wk6gg2ewo3jg0","list_name":"Pulitzer Prize for Fiction","list_slug":"pulitzer-prize-fiction","list_year":2024,"list_year_buid":"6jgqmh","list_year_extended_display_name":"","list_year_name":"2024 Pulitzer Prize for Fiction","list_year_slug":"","list_year_source":"https://www.pulitzer.org/prize-winners-by-category/219","short_description":""},{"awards_year":2024,"collectionId":"pbc_1952181814","collectionName":"view_list_year_details","created":"2025-02-16 08:49:31.405Z","id":"378hrf67f62r28e","list_id":"g4j4v5so8mc5r5a","list_name":"Kirkus Prize","list_slug":"kirkus-prize","list_year":2024,"list_year_buid":"hnfwfj","list_year_extended_display_name":"","list_year_name":"2024 Kirkus Prize","list_year_slug":"","list_year_source":"https://www.kirkusreviews.com/prize/2024/","short_description":""},{"awards_year":2023,"collectionId":"pbc_1952181814","collectionName":"view_list_year_details","created":"2025-02-16 09:11:23.100Z","id":"0q9870spg4qc5un","list_id":"g4j4v5so8mc5r5a","list_name":"Kirkus Prize","list_slug":"kirkus-prize","list_year":2023,"list_year_buid":"nfwqzp","list_year_extended_display_name":"","list_year_name":"2023 Kirkus Prize","list_year_slug":"","list_year_source":"https://www.kirkusreviews.com/prize/2023/","short_description":""},{"awards_year":2024,"collectionId":"pbc_1952181814","collectionName":"view_list_year_details","created":"2025-02-16 09:47:14.897Z","id":"q6s86t1j4xeziq2","list_id":"3196z5jzvz02db2","list_name":"Women's Prize for Fiction","list_slug":"womens-prize-fiction","list_year":2024,"list_year_buid":"tqzf7z","list_year_extended_display_name":"","list_year_name":"2024 Women's Prize for Fiction","list_year_slug":"","list_year_source":"https://womensprize.com/prizes/womens-prize-for-fiction/","short_description":""},{"awards_year":2023,"collectionId":"pbc_1952181814","collectionName":"view_list_year_details","created":"2025-02-17 06:58:15.793Z","id":"2oplocs19r1v07m","list_id":"5de40u61vhz3hei","list_name":"Tournament of Books","list_slug":"tournament-of-books","list_year":2023,"list_year_buid":"cdf9jt","list_year_extended_display_name":"","list_year_name":"2023 Tournament of Books","list_year_slug":"","list_year_source":"https://www.tournamentofbooks.com/the-year-in-fiction-2023","short_description":""},{"awards_year":2024,"collectionId":"pbc_1952181814","collectionName":"view_list_year_details","created":"2025-02-17 07:21:54.318Z","id":"6yf98386377ihm8","list_id":"4245qerp050lt8b","list_name":"Canada Reads","list_slug":"canada-reads","list_year":2024,"list_year_buid":"zcrnzm","list_year_extended_display_name":"","list_year_name":"2024 Canada Reads","list_year_slug":"","list_year_source":"https://www.cbc.ca/books/canadareads/past-canada-reads-contenders-and-winners-1.4034451","short_description":""},{"awards_year":2024,"collectionId":"pbc_1952181814","collectionName":"view_list_year_details","created":"2025-02-17 07:53:14.435Z","id":"96ft4m299m9r48m","list_id":"wo3d0t8gi3ny6fv","list_name":"Carol Shields Prize","list_slug":"carol-shields-prize","list_year":2024,"list_year_buid":"wdb7n7","list_year_extended_display_name":"","list_year_name":"2024 Carol Shields Prize","list_year_slug":"","list_year_source":"https://carolshieldsprizeforfiction.com/2024-shortlist","short_description":""},{"awards_year":2023,"collectionId":"pbc_1952181814","collectionName":"view_list_year_details","created":"2025-02-17 08:34:41.173Z","id":"933ba3byhc5814n","list_id":"4245qerp050lt8b","list_name":"Canada Reads","list_slug":"canada-reads","list_year":2023,"list_year_buid":"6q7dfb","list_year_extended_display_name":"","list_year_name":"2023 Canada Reads","list_year_slug":"","list_year_source":"https://www.cbc.ca/books/canadareads/mattea-roach-championing-ducks-by-kate-beaton-wins-canada-reads-2023-1.6795030","short_description":""},{"awards_year":2023,"collectionId":"pbc_1952181814","collectionName":"view_list_year_details","created":"2025-02-17 08:53:49.068Z","id":"nng77a7p6tfs2un","list_id":"r204xjwf2flc2k3","list_name":"National Book Award","list_slug":"national-book-award","list_year":2023,"list_year_buid":"8zpk98","list_year_extended_display_name":"","list_year_name":"2023 National Book Award","list_year_slug":"","list_year_source":"https://www.nationalbook.org/awards-prizes/national-book-awards-2023/","short_description":""},{"awards_year":2024,"collectionId":"pbc_1952181814","collectionName":"view_list_year_details","created":"2025-02-21 09:16:45.744Z","id":"tf7997cg26j6261","list_id":"hkud3a805p313zg","list_name":"New York Times Best Books","list_slug":"nytimes-best-books","list_year":2024,"list_year_buid":"h6fkz6","list_year_extended_display_name":"","list_year_name":"2024 New York Times Best Books","list_year_slug":"","list_year_source":"https://www.nytimes.com/interactive/2024/books/top-books-list.html","short_description":""},{"awards_year":2023,"collectionId":"pbc_1952181814","collectionName":"view_list_year_details","created":"2025-02-24 20:19:39.429Z","id":"9n4a6b5s52vg230","list_id":"hkud3a805p313zg","list_name":"New York Times Best Books","list_slug":"nytimes-best-books","list_year":2023,"list_year_buid":"ttnqh6","list_year_extended_display_name":"","list_year_name":"2023 New York Times Best Books","list_year_slug":"","list_year_source":"https://www.newyorker.com/best-books-2023","short_description":""}]